switchforpython/__init__.py
switchforpython-0.1.2.dist-info/WHEEL
switchforpython-0.1.2.dist-info/METADATA
switchforpython-0.1.2.dist-info/RECORD
