Metadata-Version: 2.1
Name: switchforpython
Version: 0.1.2
Summary: Switch statements in python 3.x
Author: Python Nerd
Author-email: prajwalmisc@gmail.com
Requires-Python: >=3.0
Classifier: Programming Language :: Python :: 3
Classifier: Programming Language :: Python :: 3.10
Classifier: Programming Language :: Python :: 3.4
Classifier: Programming Language :: Python :: 3.5
Classifier: Programming Language :: Python :: 3.6
Classifier: Programming Language :: Python :: 3.7
Classifier: Programming Language :: Python :: 3.8
Classifier: Programming Language :: Python :: 3.9
